licvault/main.py
licvault-0.1.0.dist-info/METADATA
licvault-0.1.0.dist-info/WHEEL
licvault-0.1.0.dist-info/RECORD
