Metadata-Version: 2.4
Name: licvault
Version: 0.1.0
Summary: license vault
Author: HSIAOLIN
Maintainer-email: HSIAOLIN <sjzshmh@163.com>
License: MIT
Keywords: license,manager
Classifier: Development Status :: 4 - Beta
Classifier: Intended Audience :: Developers
Classifier: License :: OSI Approved :: MIT License
Classifier: Programming Language :: Python :: 3
Classifier: Programming Language :: Python :: 3.10
Requires-Python: >=3.10
